PyCyberUtils/__init__.py
PyCyberUtils/easy.py
PyCyberUtils/exceptions.py
PyCyberUtils/models.py
PyCyberUtils-0.3.8.dist-info/METADATA
PyCyberUtils-0.3.8.dist-info/WHEEL
PyCyberUtils-0.3.8.dist-info/top_level.txt
PyCyberUtils-0.3.8.dist-info/RECORD
