Metadata-Version: 2.1
Name: PyCyberUtils
Version: 0.3.8
Summary: Hacking Team main utils library
Author: ConnorDev
License: MIT
Platform: UNKNOWN
